caspar_church/caspar_church.py
caspar_church/CC_Utility.py
caspar_church/HTML Templates.zip
caspar_church/Widget_frames.py
caspar_church-0.0.1.dist-info/LICENSE
caspar_church-0.0.1.dist-info/LICENSE.txt
caspar_church-0.0.1.dist-info/LICENSE.rst
caspar_church-0.0.1.dist-info/WHEEL
caspar_church-0.0.1.dist-info/METADATA
caspar_church-0.0.1.dist-info/RECORD
