Metadata-Version: 2.1
Name: caspar-church
Version: 0.0.1
Summary: A CasparCG client designed for displaying lyrics, bible verses and video on multiple outputs.
License: GPL
Author: Jeffrey Rydell
Requires-Python: >=3.8,<4.0
Classifier: License :: Other/Proprietary License
Classifier: Programming Language :: Python :: 3
Classifier: Programming Language :: Python :: 3.8
Classifier: Programming Language :: Python :: 3.9
Classifier: Programming Language :: Python :: 3.10
Requires-Dist: amcp-pylib (>=0.2.2,<0.3.0)
Requires-Dist: bible3 (>=1.0.0,<2.0.0)
Requires-Dist: python-scriptures (>=3.0.0,<4.0.0)
Requires-Dist: striprtf (>=0.0.21,<0.0.22)
